codechefcli/__init__.py
codechefcli/__init__.pyc
codechefcli/__main__.py
codechefcli/__main__.pyc
codechefcli/auth.py
codechefcli/auth.pyc
codechefcli/decorators.py
codechefcli/helpers.py
codechefcli/problems.py
codechefcli/teams.py
codechefcli/users.py
codechefcli/__pycache__/__init__.cpython-38.pyc
codechefcli/__pycache__/__main__.cpython-38.pyc
codechefcli/__pycache__/auth.cpython-38.pyc
codechefcli/__pycache__/decorators.cpython-38.pyc
codechefcli/__pycache__/helpers.cpython-38.pyc
codechefcli/__pycache__/problems.cpython-38.pyc
codechefcli/__pycache__/teams.cpython-38.pyc
codechefcli/__pycache__/users.cpython-38.pyc
codechefcli/utils/__init__.py
codechefcli/utils/constants.py
codechefcli/utils/helpers.py
codechefcli/utils/__pycache__/__init__.cpython-38.pyc
codechefcli/utils/__pycache__/constants.cpython-38.pyc
codechefcli/utils/__pycache__/helpers.cpython-38.pyc
codechefcli-0.5.3.dist-info/LICENSE
codechefcli-0.5.3.dist-info/METADATA
codechefcli-0.5.3.dist-info/WHEEL
codechefcli-0.5.3.dist-info/entry_points.txt
codechefcli-0.5.3.dist-info/top_level.txt
codechefcli-0.5.3.dist-info/RECORD
