Metadata-Version: 2.1
Name: codechefcli
Version: 0.5.3
Summary: CodeChef Command Line Interface
Home-page: http://www.github.com/sk364/codechef-cli
Author: Sachin Kukreja
Author-email: skad5455@gmail.com
License: GNU
Keywords: codechefcli codechef cli programming competitive-programming competitive-coding
Platform: UNKNOWN
Requires-Python: >=3.6
Requires-Dist: requests-html
